setup.py
client/__init__.py
client/client.py
client/client/__init__.py
client/client/add_contact.py
client/client/database.py
client/client/del_contact.py
client/client/main_window.py
client/client/main_window_conv.py
client/client/start_dialog.py
client/client/transport.py
client/commons/__init__.py
client/commons/decorators.py
client/commons/descriptors.py
client/commons/errors.py
client/commons/metaclasses.py
client/commons/utils.py
client/commons/variables.py
client/logs/__init__.py
client/logs/config_client_logs.py
client/logs/config_server_logs.py
server_chat_app.egg-info/PKG-INFO
server_chat_app.egg-info/SOURCES.txt
server_chat_app.egg-info/dependency_links.txt
server_chat_app.egg-info/requires.txt
server_chat_app.egg-info/top_level.txt