Metadata-Version: 2.1
Name: server-chat-app
Version: 0.0.1
Summary: server
Author: dmitrycider
Author-email: dimkasidorow@gmail.com
